surepy/__init__.py
surepy/client.py
surepy/const.py
surepy/entities/__init__.py
surepy/entities/devices.py
surepy/entities/pet.py
surepy/entities/states.py
surepy/enums.py
surepy/exceptions.py
surepy/py.typed
surepy/surecli/__init__.py
surepy-0.8.0.dist-info/entry_points.txt
surepy-0.8.0.dist-info/LICENSE
surepy-0.8.0.dist-info/WHEEL
surepy-0.8.0.dist-info/METADATA
surepy-0.8.0.dist-info/RECORD
