Metadata-Version: 2.1
Name: surepy
Version: 0.8.0
Summary: Library to interact with the flaps & doors from Sure Petcare.
Home-page: https://github.com/benleb/surepy
License: MIT
Keywords: cat,surepetcare,home-assistant
Author: Ben Lebherz
Author-email: git@benleb.de
Requires-Python: >=3.8.0,<4.0.0
Classifier: Development Status :: 4 - Beta
Classifier: Development Status :: 5 - Production/Stable
Classifier: Environment :: Console
Classifier: Intended Audience :: Developers
Classifier: Intended Audience :: End Users/Desktop
Classifier: License :: OSI Approved :: MIT License
Classifier: Operating System :: OS Independent
Classifier: Programming Language :: Python
Classifier: Programming Language :: Python :: 3
Classifier: Programming Language :: Python :: 3.8
Classifier: Programming Language :: Python :: 3.9
Classifier: Programming Language :: Python :: 3.10
Classifier: Programming Language :: Python :: 3.8
Classifier: Programming Language :: Python :: 3.9
Classifier: Topic :: Home Automation
Classifier: Topic :: Software Development
Classifier: Topic :: Software Development :: Libraries :: Python Modules
Requires-Dist: aiohttp[speedups] (>=3.7.4,<4.0.0)
Requires-Dist: async-timeout (>=3.0.1,<5.0)
Requires-Dist: click (>=7.1.2,<9.0.0)
Requires-Dist: requests (>=2.24.0,<3.0.0)
Requires-Dist: rich (>=10.1.0,<11.0.0)
Project-URL: Documentation, https://surepy.readthedocs.io
Project-URL: Repository, https://github.com/benleb/surepy
